pipeline_sdk_test25/__init__.py
pipeline_sdk_test25/auth_service.py
pipeline_sdk_test25/inference_pipeline.py
pipeline_sdk_test25/model_inference_dsl_component.py
pipeline_sdk_test25/model_train_dsl_component.py
pipeline_sdk_test25/model_validate_dsl_component.py
pipeline_sdk_test25/pipeline_util.py
pipeline_sdk_test25/run_inference_pipeline.py
pipeline_sdk_test25/run_training_pipeline.py
pipeline_sdk_test25/run_validate_pipeline.py
pipeline_sdk_test25/train_pipeline.py
pipeline_sdk_test25/validate_pipeline.py
pipeline_sdk_test25-2.0.0.dist-info/METADATA
pipeline_sdk_test25-2.0.0.dist-info/WHEEL
pipeline_sdk_test25-2.0.0.dist-info/top_level.txt
pipeline_sdk_test25-2.0.0.dist-info/RECORD
